[
  {
    "title": "My story category",
    "description": "This is my story category",
    "date": "2023-05-10",
    "category": "my story",
    "path": "mystory-01",
    "featured": false
  },
  {
    "title": "Develop category",
    "description": "This is develop category",
    "date": "2022-05-08",
    "category": "develop",
    "path": "develop-01",
    "featured": false
  },
  {
    "title": "Develop category 02",
    "description": "This is develop category",
    "date": "2022-05-09",
    "category": "develop",
    "path": "develop-02",
    "featured": true
  },
  {
    "title": "My story category 2",
    "description": "This is my story category 2",
    "date": "2023-05-11",
    "category": "my story",
    "path": "mystory-02",
    "featured": false
  },
  {
    "title": "Develop category 03",
    "description": "This is develop category",
    "date": "2022-05-11",
    "category": "develop",
    "path": "develop-03",
    "featured": true
  },
  {
    "title": "My story category 3",
    "description": "This is my story category",
    "date": "2023-05-13",
    "category": "my story",
    "path": "mystory-03",
    "featured": true
  }
]
